Workbook

Sheet Planilha1
C13: CONFIGURAÇÕES
B14: Salário | G14: 2.5
B15: Rendimento da Carteira | G15: 0.0075
B16: Sugestão de Investimento (40%) | G16: 800
C19: INVESTIMENTO MENSAL
B20: Investimento Mensal | G20: 700
B21: Período em Anos | G21: 7
B22: Rendimento Mensal | G22: 0.0103
B24: Patrimônio Acumulado | G24: =FV(G22,G21*12,G20*-1) -> 92766.437
B25: Dividendos | G25: =G24*G22 -> 955.49431
C28: PROJEÇÃO E DIVIDENDOS
B29: 2 Anos | D29: =FV(G22,2*12,G20*-1) -> 18948.742 | G29: =D29*1.03% -> 195.17205
B30: 5 Anos | D30: =FV(G22,5*12,G20*-1) -> 57723.414 | G30: =D30*1.03% -> 594.55116
B31: 10 Anos | D31: =FV(G22,10*12,G20*-1) -> 164474.72 | G31: =D31*1.03% -> 1694.0896
B32: 15 Anos | D32: =FV(G22,15*12,G20*-1) -> 361896.18 | G32: =D32*1.03% -> 3727.5307
B33: 20 Anos | D33: =FV(G22,20*12,G20*-1) -> 726999.3 | G33: =D33*1.03% -> 7488.0928
B36: Perfil | G36: Agressivo
B37: Valor a ser Investido por Mês | G37: =G20 -> 700
B40: Tipos de FII | E40: % Sugerido | G40: Valores
B41: PAPEL | E41: =VLOOKUP($G$36&"-"&B41,Planilha2!$B:$F,5,FALSE) -> 0.5 | G41: =E41*$G$37 -> 350
B42: TIJOLO | E42: =VLOOKUP($G$36&"-"&B42,Planilha2!$B:$F,5,FALSE) -> 0.1 | G42: =E42*$G$37 -> 70
B43: HÍBRIDOS | E43: =VLOOKUP($G$36&"-"&B43,Planilha2!$B:$F,5,FALSE) -> 0.05 | G43: =E43*$G$37 -> 35
B44: FOFs | E44: =VLOOKUP($G$36&"-"&B44,Planilha2!$B:$F,5,FALSE) -> 0.05 | G44: =E44*$G$37 -> 35
B45: DESENVOLVIMENTO | E45: =VLOOKUP($G$36&"-"&B45,Planilha2!$B:$F,5,FALSE) -> 0.2 | G45: =E45*$G$37 -> 140
B46: HOTERALIAS | E46: =VLOOKUP($G$36&"-"&B46,Planilha2!$B:$F,5,FALSE) -> 0.1 | G46: =E46*$G$37 -> 70
B48: TOTAL | G48: =SUM(G41:G46) -> 700

Sheet Planilha2
B3: CHAVE | C3: PERFIS | F3: %
B5: =C5&"-"&D5 -> Conservador-PAPEL | C5: Conservador | D5: PAPEL | F5: 0.3
B6: =C6&"-"&D6 -> Conservador-TIJOLO | C6: Conservador | D6: TIJOLO | F6: 0.5
B7: =C7&"-"&D7 -> Conservador-HÍBRIDOS | C7: Conservador | D7: HÍBRIDOS | F7: 0.1
B8: =C8&"-"&D8 -> Conservador-FOFs | C8: Conservador | D8: FOFs | F8: 0.1
B9: =C9&"-"&D9 -> Conservador-DESENVOLVIMENTO | C9: Conservador | D9: DESENVOLVIMENTO | F9: 0 | H9: Conservador-PAPEL | I9: %
B10: =C10&"-"&D10 -> Conservador-HOTERALIAS | C10: Conservador | D10: HOTERALIAS | F10: 0 | H10: =VLOOKUP(H9,B:F,5,FALSE) -> 0.3
B12: =C12&"-"&D12 -> Moderado-PAPEL | C12: Moderado | D12: PAPEL | F12: 0.32
B13: =C13&"-"&D13 -> Moderado-TIJOLO | C13: Moderado | D13: TIJOLO | F13: 0.35
B14: =C14&"-"&D14 -> Moderado-HÍBRIDOS | C14: Moderado | D14: HÍBRIDOS | F14: 0.08
B15: =C15&"-"&D15 -> Moderado-FOFs | C15: Moderado | D15: FOFs | F15: 0.05
B16: =C16&"-"&D16 -> Moderado-DESENVOLVIMENTO | C16: Moderado | D16: DESENVOLVIMENTO | F16: 0.1
B17: =C17&"-"&D17 -> Moderado-HOTERALIAS | C17: Moderado | D17: HOTERALIAS | F17: 0.1
B19: =C19&"-"&D19 -> Agressivo-PAPEL | C19: Agressivo | D19: PAPEL | F19: 0.5
B20: =C20&"-"&D20 -> Agressivo-TIJOLO | C20: Agressivo | D20: TIJOLO | F20: 0.1
B21: =C21&"-"&D21 -> Agressivo-HÍBRIDOS | C21: Agressivo | D21: HÍBRIDOS | F21: 0.05
B22: =C22&"-"&D22 -> Agressivo-FOFs | C22: Agressivo | D22: FOFs | F22: 0.05
B23: =C23&"-"&D23 -> Agressivo-DESENVOLVIMENTO | C23: Agressivo | D23: DESENVOLVIMENTO | F23: 0.2
B24: =C24&"-"&D24 -> Agressivo-HOTERALIAS | C24: Agressivo | D24: HOTERALIAS | F24: 0.1
